README.md
pyproject.toml
setup.py
ntdrt_pychromedevtools/__init__.py
ntdrt_pychromedevtools.egg-info/PKG-INFO
ntdrt_pychromedevtools.egg-info/SOURCES.txt
ntdrt_pychromedevtools.egg-info/dependency_links.txt
ntdrt_pychromedevtools.egg-info/not-zip-safe
ntdrt_pychromedevtools.egg-info/requires.txt
ntdrt_pychromedevtools.egg-info/top_level.txt