Metadata-Version: 2.4
Name: ntdrt-pychromedevtools
Version: 1.0.2
Author: Tomáš Kolinger
Author-email: tomas@kolinger.name
License: MIT
Requires-Dist: requests
Requires-Dist: websocket-client
Dynamic: author
Dynamic: author-email
Dynamic: description
Dynamic: description-content-type
Dynamic: license
Dynamic: requires-dist
